streamlit_carousel_uui/__init__.py
streamlit_carousel_uui/frontend/build/asset-manifest.json
streamlit_carousel_uui/frontend/build/index.html
streamlit_carousel_uui/frontend/build/static/css/main.1fec3627.css
streamlit_carousel_uui/frontend/build/static/css/main.1fec3627.css.map
streamlit_carousel_uui/frontend/build/static/js/main.fe6678c4.js
streamlit_carousel_uui/frontend/build/static/js/main.fe6678c4.js.LICENSE.txt
streamlit_carousel_uui/frontend/build/static/js/main.fe6678c4.js.map
streamlit_carousel_uui-0.1.4.dist-info/licenses/LICENSE
streamlit_carousel_uui-0.1.4.dist-info/METADATA
streamlit_carousel_uui-0.1.4.dist-info/WHEEL
streamlit_carousel_uui-0.1.4.dist-info/top_level.txt
streamlit_carousel_uui-0.1.4.dist-info/RECORD
