Metadata-Version: 2.4
Name: streamlit-carousel-uui
Version: 0.1.4
Summary: A Streamlit component for displaying an Untitled UI styled carousel
Home-page: https://github.com/janduplessis883/streamlit_carousel_uui
Author: Jan du Plessis
Author-email: 
Classifier: Programming Language :: Python :: 3
Classifier: License :: OSI Approved :: MIT License
Classifier: Operating System :: OS Independent
Requires-Python: >=3.7
License-File: LICENSE
Requires-Dist: streamlit>=1.0.0
Dynamic: author
Dynamic: classifier
Dynamic: description
Dynamic: description-content-type
Dynamic: home-page
Dynamic: license-file
Dynamic: requires-dist
Dynamic: requires-python
Dynamic: summary
